odfit
