Metadata-Version: 1.0
Name: odfit
Version: 0.6.2
Summary:  Produces textual information based on the contents of OpenDocument Format files and other archives.
Home-page: http://github.com/intuited/odfit
Author: Ted Tibbetts
Author-email: intuited@gmail.com
License: UNKNOWN
Keywords: xml,opendocument,odt,ods,odb,odp,openoffice,archive,zip,dump,diff,compare
Platform: UNKNOWN
Classifier: Development Status :: 4 - Beta
Classifier: Intended Audience :: Developers
Classifier: License :: OSI Approved :: BSD License
Classifier: Operating System :: OS Independent
Classifier: Programming Language :: Python
Classifier: Programming Language :: Python :: 2
Classifier: Topic :: Software Development :: Libraries :: Python Modules
Classifier: Topic :: Utilities
Classifier: Topic :: System :: Archiving
Classifier: Topic :: Office/Business
Classifier: Topic :: Software Development :: Version Control
